hotpot_km/__init__.py
hotpot_km/_version.py
hotpot_km/async_utils.py
hotpot_km/client_helper.py
hotpot_km/limited.py
hotpot_km/mapping.py
hotpot_km/mapping_sync.py
hotpot_km/pooled.py
hotpot_km/pooled_sync.py
hotpot_km/py_snippets.py
hotpot_km/tests/__init__.py
hotpot_km/tests/conftest.py
hotpot_km/tests/test_in_server.py
hotpot_km/tests/test_initialize.py
hotpot_km/tests/test_limited_manager.py
hotpot_km/tests/test_limited_manager_sync.py
hotpot_km/tests/test_mapping.py
hotpot_km/tests/test_mapping_sync.py
hotpot_km/tests/test_pooled_manager.py
hotpot_km/tests/test_pooled_manager_sync.py
hotpot_km/tests/test_update.py
hotpot_km/tests/utils.py
hotpot_km/tests/utils_sync.py
hotpot_km-0.2.2.dist-info/LICENSE
hotpot_km-0.2.2.dist-info/WHEEL
hotpot_km-0.2.2.dist-info/METADATA
hotpot_km-0.2.2.dist-info/RECORD
